gpl_wrapper/__about__.py
gpl_wrapper/__init__.py
gpl_wrapper/__main__.py
gpl_wrapper/snk.yaml
gpl_wrapper/cli/__init__.py
gpl_wrapper/workflow/Snakefile
gpl_wrapper/workflow/resources/get_config.py
gpl_wrapper/workflow/resources/gridss-purple-linx-nf/.bumpversion.cfg
gpl_wrapper/workflow/resources/gridss-purple-linx-nf/.flake8
gpl_wrapper/workflow/resources/gridss-purple-linx-nf/.gitignore
gpl_wrapper/workflow/resources/gridss-purple-linx-nf/.mdl_style.rb
gpl_wrapper/workflow/resources/gridss-purple-linx-nf/.mdlrc
gpl_wrapper/workflow/resources/gridss-purple-linx-nf/.pre-commit-config.yaml
gpl_wrapper/workflow/resources/gridss-purple-linx-nf/.pylintrc
gpl_wrapper/workflow/resources/gridss-purple-linx-nf/main.nf
gpl_wrapper/workflow/resources/gridss-purple-linx-nf/.github/workflows/lint.yaml
gpl_wrapper/workflow/resources/gridss-purple-linx-nf/lib/utility.groovy
gpl_wrapper/workflow/resources/gridss-purple-linx-nf/modules/local/amber.nf
gpl_wrapper/workflow/resources/gridss-purple-linx-nf/modules/local/cobalt.nf
gpl_wrapper/workflow/resources/gridss-purple-linx-nf/modules/local/gridss_annotate.nf
gpl_wrapper/workflow/resources/gridss-purple-linx-nf/modules/local/gridss_assemble.nf
gpl_wrapper/workflow/resources/gridss-purple-linx-nf/modules/local/gridss_call.nf
gpl_wrapper/workflow/resources/gridss-purple-linx-nf/modules/local/gridss_extract_fragments.nf
gpl_wrapper/workflow/resources/gridss-purple-linx-nf/modules/local/gridss_preprocess.nf
gpl_wrapper/workflow/resources/gridss-purple-linx-nf/modules/local/gripss.nf
gpl_wrapper/workflow/resources/gridss-purple-linx-nf/modules/local/linx_annotation.nf
gpl_wrapper/workflow/resources/gridss-purple-linx-nf/modules/local/linx_visualiser.nf
gpl_wrapper/workflow/resources/gridss-purple-linx-nf/modules/local/purple.nf
gpl_wrapper/workflow/resources/gridss-purple-linx-nf/modules/local/report.nf
gpl_wrapper/workflow/resources/gridss-purple-linx-nf/subworkflows/gridss.nf
gpl_wrapper-0.1.1.dist-info/METADATA
gpl_wrapper-0.1.1.dist-info/WHEEL
gpl_wrapper-0.1.1.dist-info/entry_points.txt
gpl_wrapper-0.1.1.dist-info/licenses/LICENSE.txt
gpl_wrapper-0.1.1.dist-info/RECORD
