Metadata-Version: 2.1
Name: gpl-wrapper
Version: 0.1.1
Project-URL: Documentation, https://github.com/pbousquets/gpl-wrapper#readme
Project-URL: Issues, https://github.com/pbousquets/gpl-wrapper/issues
Project-URL: Source, https://github.com/pbousquets/gpl-wrapper
Author-email: pbousquets <pbousquetsm@gmail.com>
License-Expression: MIT
License-File: LICENSE.txt
Classifier: Development Status :: 4 - Beta
Classifier: Programming Language :: Python
Classifier: Programming Language :: Python :: 3.8
Classifier: Programming Language :: Python :: 3.9
Classifier: Programming Language :: Python :: 3.10
Classifier: Programming Language :: Python :: 3.11
Classifier: Programming Language :: Python :: 3.12
Classifier: Programming Language :: Python :: Implementation :: CPython
Classifier: Programming Language :: Python :: Implementation :: PyPy
Requires-Python: >=3.8
Requires-Dist: snk
